[{"province":"湖北省","city":"孝感市","area":"孝昌县","name":"发展大道邮政支局","code":"432999","address":"湖北省孝感市孝昌县花园镇西洪花路16号","phone":"0712-4765333"},{"province":"湖北省","city":"孝感市","area":"孝昌县","name":"洪花路邮政支局","code":"432999","address":"湖北省孝昌县花园大道27号","phone":"13733440910"},{"province":"湖北省","city":"孝感市","area":"孝昌县","name":"中天大道邮政支局","code":"432999","address":"湖北省孝感市孝昌县中天大道126号","phone":"0712-4898689"},{"province":"湖北省","city":"孝感市","area":"孝昌县","name":"古城大道邮政支局","code":"432999","address":"湖北省孝感市孝昌县古城大道41号","phone":"18871228582"}]